dataio/__init__.py
bpx_dataio-0.1.1.dist-info/METADATA
bpx_dataio-0.1.1.dist-info/WHEEL
bpx_dataio-0.1.1.dist-info/top_level.txt
bpx_dataio-0.1.1.dist-info/RECORD
