Metadata-Version: 2.4
Name: bpx-dataio
Version: 0.1.1
Summary: Useful utilities for data IO operations, including Snowflake, S3, and SageMaker integrations.
Home-page: https://github.com/bpx/bpx-dataio
Author: Julian Liu
Author-email: Julian Liu <data.intelligence.mastery@gmail.com>
License: MIT
Keywords: data-io,snowflake,s3,sagemaker,aws,bpx
Classifier: Development Status :: 3 - Alpha
Classifier: Intended Audience :: Developers
Classifier: Intended Audience :: Science/Research
Classifier: License :: OSI Approved :: MIT License
Classifier: Programming Language :: Python :: 3
Classifier: Programming Language :: Python :: 3.7
Classifier: Programming Language :: Python :: 3.8
Classifier: Programming Language :: Python :: 3.9
Classifier: Programming Language :: Python :: 3.10
Classifier: Programming Language :: Python :: 3.11
Classifier: Topic :: Scientific/Engineering
Classifier: Topic :: Software Development :: Libraries :: Python Modules
Requires-Python: >=3.7
Requires-Dist: boto3>=1.26.0
Requires-Dist: snowflake-connector-python[pandas]>=3.0.0
Requires-Dist: certifi>=2022.0.0
Requires-Dist: pandas>=1.5.0
Requires-Dist: numpy>=1.23.0
Requires-Dist: scikit-learn>=1.0.0
Dynamic: author
Dynamic: home-page
Dynamic: requires-python
